[
  {
    "UserEmail": "danylo.hladkov@nure.ua",
    "Firstname": "Danylo",
    "Lastname": "Hladkov",
    "WorkedHours": 12,
    "WastedHours": 1,
    "Department": {
      "DepartmentName": ".NET"
    },
    "Schedules": [
      {
        "WeekDayId": 1,
        "TimeFrom": "06:00",
        "TimeTo": "20:00"
      }
    ],
    "WastedMinutes": 59,
    "WorkedMinutes": 59
  },
  {
    "UserEmail": "raymondsullivan@kraggle.com",
    "Firstname": "Mabel",
    "Lastname": "Howe",
    "WorkedHours": 4,
    "WastedHours": 2,
    "Department": {
      "DepartmentName": "Java"
    },
    "Schedules": [
      {
        "WeekDayId": 7,
        "TimeFrom": "08:00",
        "TimeTo": "16:00"
      }
    ],
    "WastedMinutes": 0,
    "WorkedMinutes": 0
  },
  {
    "UserEmail": "mabelhowe@kraggle.com",
    "Firstname": "Daisy",
    "Lastname": "Cooper",
    "WorkedHours": 8,
    "WastedHours": 0,
    "Department": {
      "DepartmentName": "IOS"
    },
    "Schedules": [
      {
        "WeekDayId": 4,
        "TimeFrom": "08:00",
        "TimeTo": "16:00"
      }
    ],
    "WastedMinutes": 0,
    "WorkedMinutes": 0
  },
  {
    "UserEmail": "daisycooper@kraggle.com",
    "Firstname": "Amie",
    "Lastname": "William",
    "WorkedHours": 4,
    "WastedHours": 2,
    "Department": {
      "DepartmentName": "Embedded Systems"
    },
    "Schedules": [
      {
        "WeekDayId": 6,
        "TimeFrom": "08:00",
        "TimeTo": "16:00"
      }
    ],
    "WastedMinutes": 0,
    "WorkedMinutes": 0
  },
  {
    "UserEmail": "amiewilliam@kraggle.com",
    "Firstname": "Trina",
    "Lastname": "Cervantes",
    "WorkedHours": 8,
    "WastedHours": 2,
    "Department": {
      "DepartmentName": ".NET"
    },
    "Schedules": [
      {
        "WeekDayId": 7,
        "TimeFrom": "08:00",
        "TimeTo": "20:00"
      }
    ],
    "WastedMinutes": 0,
    "WorkedMinutes": 0
  }
]